django_otto_admin-0.1.2.dist-info/DESCRIPTION.rst
django_otto_admin-0.1.2.dist-info/METADATA
django_otto_admin-0.1.2.dist-info/RECORD
django_otto_admin-0.1.2.dist-info/WHEEL
django_otto_admin-0.1.2.dist-info/metadata.json
django_otto_admin-0.1.2.dist-info/top_level.txt
otto_admin/__init__.py
otto_admin/tests.py
otto_admin/locale/it/LC_MESSAGES/django.mo
otto_admin/locale/it/LC_MESSAGES/django.po
otto_admin/static/otto_admin/css/dashboard.css
otto_admin/templates/admin/base.html
otto_admin/templates/admin/index.html
otto_admin/templates/otto_admin/analytics.html
otto_admin/templatetags/__init__.py
otto_admin/templatetags/otto_admin_tags.py
