Metadata-Version: 2.0
Name: django-otto-admin
Version: 0.1.2
Summary: Django admin customization app for django-suit providing google analytics widgets in the admin index
Home-page: http://github.com/otto-torino/django-otto-admin
Author: abidibo
Author-email: abidibo@gmail.com
License: MIT License
Platform: UNKNOWN
Classifier: Environment :: Web Environment
Classifier: Framework :: Django
Classifier: Intended Audience :: Developers
Classifier: Intended Audience :: System Administrators
Classifier: License :: OSI Approved :: MIT License
Classifier: Operating System :: OS Independent
Classifier: Programming Language :: Python
Classifier: Programming Language :: Python :: 2.5
Classifier: Programming Language :: Python :: 2.6
Classifier: Programming Language :: Python :: 2.7
Classifier: Programming Language :: Python :: 3.2
Classifier: Programming Language :: Python :: 3.3
Classifier: Topic :: Software Development
Classifier: Topic :: Software Development :: User Interfaces
Requires-Dist: Django
Requires-Dist: django-suit
Requires-Dist: google-api-python-client
Requires-Dist: oauth2client (==1.5.2)
